terracomp_typer/__init__.py
terracomp_typer/_build.py
terracomp_typer/_build_test.py
terracomp_typer/_injector.py
terracomp_typer/py.typed
terracomp_typer-0.0.8.dist-info/LICENSE
terracomp_typer-0.0.8.dist-info/METADATA
terracomp_typer-0.0.8.dist-info/WHEEL
terracomp_typer-0.0.8.dist-info/RECORD
