Metadata-Version: 2.1
Name: terracomp-typer
Version: 0.0.8
Summary: 
License: MIT
Author: Niklas Rosenstein
Author-email: rosensteinniklas@gmail.com
Requires-Python: >=3.7,<4.0
Classifier: License :: OSI Approved :: MIT License
Classifier: Programming Language :: Python :: 3
Classifier: Programming Language :: Python :: 3.7
Classifier: Programming Language :: Python :: 3.8
Classifier: Programming Language :: Python :: 3.9
Classifier: Programming Language :: Python :: 3.10
Classifier: Programming Language :: Python :: 3.11
Requires-Dist: nr-stream (>=1.1.5,<2.0.0)
Requires-Dist: typeapi (>=1.4.1,<2.0.0)
Requires-Dist: typer (>=0.7.0,<0.8.0)
